PyShoreVolume/DOD1.py
PyShoreVolume/DataImportandTransectDefinition1.py
PyShoreVolume/Oceanographicplot.py
PyShoreVolume/SCA1.py
PyShoreVolume/__init__.py
PyShoreVolume/CleanandTransectLocator/DataCleaning.py
PyShoreVolume/CleanandTransectLocator/TransectDefinition.py
PyShoreVolume/CleanandTransectLocator/__init__.py
PyShoreVolume/Extra/End Point Rate.jpg
PyShoreVolume/Extra/File_Organisation_Script.py
PyShoreVolume/Extra/Intersections2.cpg
PyShoreVolume/Extra/Intersections2.dbf
PyShoreVolume/Extra/Intersections2.prj
PyShoreVolume/Extra/Intersections2.shp
PyShoreVolume/Extra/Intersections2.shx
PyShoreVolume/Extra/NetShorelineMovementErosionandAccretion.jpg
PyShoreVolume/Extra/QGISMergedShoreline.py
PyShoreVolume/Extra/Transect1.cpg
PyShoreVolume/Extra/Transect1.dbf
PyShoreVolume/Extra/Transect1.prj
PyShoreVolume/Extra/Transect1.shp
PyShoreVolume/Extra/Transect1.shx
PyShoreVolume/Extra/__init__.py
PyShoreVolume/Extra/eprresults.pkl
PyShoreVolume/Extra/lrrdictionary.pkl
PyShoreVolume/Extra/netshorelinemovement.jpg
PyShoreVolume/Extra/nsm.pkl
PyShoreVolume/Extra/scedic.pkl
PyShoreVolume/Extra/shorleinechangeenvelope.jpg
PyShoreVolume/ShorelineChange/EPR.py
PyShoreVolume/ShorelineChange/LRR.py
PyShoreVolume/ShorelineChange/NSM.py
PyShoreVolume/ShorelineChange/NSMEandA.py
PyShoreVolume/ShorelineChange/SCE.py
PyShoreVolume/ShorelineChange/__init__.py
PyShoreVolume/VolumeChanges/DEMofDifference.py
PyShoreVolume/VolumeChanges/DODSubPlot.py
PyShoreVolume/VolumeChanges/MaskingDEM.py
PyShoreVolume/VolumeChanges/NetVolumeChange.py
PyShoreVolume/VolumeChanges/OldesttoNewest.py
PyShoreVolume/VolumeChanges/SeasonalDOD.py
PyShoreVolume/VolumeChanges/__init__.py
PyShoreVolume-1.1.0.dist-info/METADATA
PyShoreVolume-1.1.0.dist-info/WHEEL
PyShoreVolume-1.1.0.dist-info/top_level.txt
PyShoreVolume-1.1.0.dist-info/RECORD
