Metadata-Version: 2.1
Name: PyShoreVolume
Version: 1.1.0
Summary: Python Based Shoreline Change and Beach Volume Analysis Tool
Home-page: https://github.com/owencaseyjames/PyShoreVolume
Author: Owen Casey James
Author-email: owen.james@kcl.ac.uk
License: MIT
Keywords: Shoreline Erosion SCA Volume Digital Elevation Model EPR SCA NSM LRR
Classifier: Development Status :: 4 - Beta
Classifier: License :: OSI Approved :: MIT License
Classifier: Programming Language :: Python :: 3
Classifier: Intended Audience :: Science/Research
Classifier: Topic :: Scientific/Engineering :: GIS
Classifier: Operating System :: OS Independent
Requires-Python: >=3
Requires-Dist: basemap-data (>=1.3.2)
Requires-Dist: contextily (>=1.3.0)
Requires-Dist: Fiona (>=1.9.1)
Requires-Dist: geopandas (>=0.9.0)
Requires-Dist: geopy (>=2.3.0)
Requires-Dist: matplotlib (>=3.7.1)
Requires-Dist: numpy (>=1.23.5)
Requires-Dist: pandas (>=1.5.3)
Requires-Dist: Pillow (>=9.4.0)
Requires-Dist: pyproj (>=3.5.0)
Requires-Dist: rasterio (>=1.3.6)
Requires-Dist: scikit-learn (>=1.2.2)
Requires-Dist: scipy (>=1.10.0)
Requires-Dist: seaborn (>=0.12.2)
Requires-Dist: shapely (>=2.0.1)
Requires-Dist: statsmodels (>=0.13.5)
